[
    {
        "_index": "624b05d6bbecdad3cf84ebaa",
        "id": 1,
        "picture": "https://i.ibb.co/591MCHw/User-1.webp",
        "name": "Sloan Bishop",
        "stars": 5,
        "body": "I have had Dell forever. They are very sturdy and you can trust them. My kids dropped them several times and they keep working. For college students they are a plus because come in many different formats. Very good job Dell. You have here a well satisfied customer. Thanks."
    },
    {
        "_index": "624b05d6c2c7c0181dcada04",
        "id": 2,
        "picture": "https://i.ibb.co/x6V6jJB/User-2.webp",
        "name": "Nell Tucker",
        "stars": 5,
        "body": "Bought many computers over the years, but Dell stands out for quality and longevity. Soon I will buy their Poweredge server, but will wait for the Black Monday discount. All other computers I bought had problems, but Dell is a solid bet."
    },
    {
        "_index": "624b05d65aa53dc4e5c7106a",
        "id": 3,
        "picture": "https://i.ibb.co/N2WqYqZ/User-3.webp",
        "name": "Hood Goodman",
        "stars": 5,
        "body": "Bought many computers over the years, but Dell stands out for quality and longevity. Soon I will buy their Poweredge server, but will wait for the Black Monday discount. All other computers I bought had problems, but Dell is a solid bet."
    },
    {
        "_index": "624b05d64e1ca1991f53775b",
        "id": 4,
        "picture": "https://i.ibb.co/85dZWr5/User-4.webp",
        "name": "Horne Carey",
        "stars": 5,
        "body": "Bought many computers over the years, but Dell stands out for quality and longevity. Soon I will buy their Poweredge server, but will wait for the Black Monday discount. All other computers I bought had problems, but Dell is a solid bet."
    },
    {
        "_index": "624b05d6d5906bf312101ac2",
        "id": 5,
        "picture": "https://i.ibb.co/cvmzsKQ/User-5.webp",
        "name": "Sweet Rivera",
        "stars": 5,
        "body": "Bought many computers over the years, but Dell stands out for quality and longevity. Soon I will buy their Poweredge server, but will wait for the Black Monday discount. All other computers I bought had problems, but Dell is a solid bet."
    },
    {
        "_index": "624b05d682c90b47fc03bb9d",
        "id": 6,
        "picture": "https://i.ibb.co/CJVhy3Q/User-6.webp",
        "name": "Kim Kardeshian",
        "stars": 5,
        "body": "Bought many computers over the years, but Dell stands out for quality and longevity. Soon I will buy their Poweredge server, but will wait for the Black Monday discount. All other computers I bought had problems, but Dell is a solid bet."
    },
    {
        "_index": "624b05d6bddd695836be86fa",
        "id": 7,
        "picture": "https://i.ibb.co/vj95tnx/User-7.webp",
        "name": "Eunice Hudson",
        "stars": 5,
        "body": "Bought many computers over the years, but Dell stands out for quality and longevity. Soon I will buy their Poweredge server, but will wait for the Black Monday discount. All other computers I bought had problems, but Dell is a solid bet."
    }
]